Workbook

Sheet Assumptions
A1: CRYPTURE FINANCIAL MODEL - ASSUMPTIONS
A3: USER GROWTH ASSUMPTIONS
B4: Conservative | C4: Moderate | D4: Aggressive
A5: Month 1 Users | B5: 500 | C5: 1000 | D5: 2000
A6: Monthly Growth Rate (Y1) | B6: 10% | C6: 15% | D6: 20%
A7: Monthly Growth Rate (Y2) | B7: 8% | C7: 12% | D7: 15%
A8: Monthly Growth Rate (Y3) | B8: 5% | C8: 8% | D8: 10%
A10: CONVERSION ASSUMPTIONS
B11: Conservative | C11: Moderate | D11: Aggressive
A12: Free → Premium (Y1) | B12: 3% | C12: 5% | D12: 7%
A13: Free → Premium (Y2) | B13: 4% | C13: 6% | D13: 9%
A14: Free → Premium (Y3) | B14: 5% | C14: 7% | D14: 10%
A15: Free → Pro (All Years) | B15: 0.5% | C15: 1% | D15: 1.5%
A18: CHURN ASSUMPTIONS
B19: Conservative | C19: Moderate | D19: Aggressive
A20: Premium Monthly Churn | B20: 6% | C20: 5% | D20: 4%
A21: Pro Monthly Churn | B21: 4% | C21: 3% | D21: 2%
A24: PRICING ASSUMPTIONS
B25: Monthly | C25: Annual | D25: Discount
A26: Premium | B26: 9.99 | C26: 99 | D26: 17%
A27: Pro | B27: 19.99 | C27: 199 | D27: 17%
A28: Annual Adoption Rate | B28: 30% | C28: 35% | D28: 40%
A31: COST ASSUMPTIONS (Monthly)
B32: Year 1 | C32: Year 2 | D32: Year 3
A33: Infrastructure | B33: 500 | C33: 2000 | D33: 5000
A34: API Costs (per 1K users) | B34: 50 | C34: 40 | D34: 30
A35: Payment Processing | B35: 2.9% + $0.30 | C35: 2.9% + $0.30 | D35: 2.9% + $0.30
A36: Support (per 1K users) | B36: 200 | C36: 150 | D36: 100

Sheet Revenue Model
A1: REVENUE MODEL - MODERATE SCENARIO
A3: YEAR 1 - MONTHLY PROJECTIONS
A4: Month | B4: Total Users | C4: Growth % | D4: Free Users | E4: Premium | F4: Pro | G4: Premium MRR | H4: Pro MRR | I4: Total MRR | J4: Premium Rev | K4: Pro Rev | L4: Total Rev
A5: 1 | B5: 1000 | D5: 940 | E5: 50 | F5: 10 | G5: =E5*Assumptions!$B$26 | H5: =F5*Assumptions!$B$27 | I5: =G5+H5
A6: 2 | B6: 1150 | C6: 0.15 | D6: 1081 | E6: 58 | F6: 12 | G6: =E6*Assumptions!$B$26 | H6: =F6*Assumptions!$B$27 | I6: =G6+H6
A7: 3 | B7: 1323 | C7: 0.15 | D7: 1243 | E7: 66 | F7: 13 | G7: =E7*Assumptions!$B$26 | H7: =F7*Assumptions!$B$27 | I7: =G7+H7
A8: 4 | B8: 1521 | C8: 0.15 | D8: 1430 | E8: 76 | F8: 15 | G8: =E8*Assumptions!$B$26 | H8: =F8*Assumptions!$B$27 | I8: =G8+H8
A9: 5 | B9: 1749 | C9: 0.15 | D9: 1644 | E9: 87 | F9: 17 | G9: =E9*Assumptions!$B$26 | H9: =F9*Assumptions!$B$27 | I9: =G9+H9
A10: 6 | B10: 2012 | C10: 0.15 | D10: 1891 | E10: 101 | F10: 20 | G10: =E10*Assumptions!$B$26 | H10: =F10*Assumptions!$B$27 | I10: =G10+H10
A11: 7 | B11: 2313 | C11: 0.15 | D11: 2175 | E11: 116 | F11: 23 | G11: =E11*Assumptions!$B$26 | H11: =F11*Assumptions!$B$27 | I11: =G11+H11
A12: 8 | B12: 2660 | C12: 0.15 | D12: 2501 | E12: 133 | F12: 27 | G12: =E12*Assumptions!$B$26 | H12: =F12*Assumptions!$B$27 | I12: =G12+H12
A13: 9 | B13: 3059 | C13: 0.15 | D13: 2876 | E13: 153 | F13: 31 | G13: =E13*Assumptions!$B$26 | H13: =F13*Assumptions!$B$27 | I13: =G13+H13
A14: 10 | B14: 3518 | C14: 0.15 | D14: 3307 | E14: 176 | F14: 35 | G14: =E14*Assumptions!$B$26 | H14: =F14*Assumptions!$B$27 | I14: =G14+H14
A15: 11 | B15: 4046 | C15: 0.15 | D15: 3803 | E15: 202 | F15: 40 | G15: =E15*Assumptions!$B$26 | H15: =F15*Assumptions!$B$27 | I15: =G15+H15
A16: 12 | B16: 4653 | C16: 0.15 | D16: 4374 | E16: 233 | F16: 47 | G16: =E16*Assumptions!$B$26 | H16: =F16*Assumptions!$B$27 | I16: =G16+H16
A18: Year 1 Total Revenue | B18: =SUM(I5:I16)
A21: YEAR 2 - QUARTERLY PROJECTIONS
A22: Quarter | B22: Total Users | C22: Free Users | D22: Premium | E22: Pro | F22: Premium MRR | G22: Pro MRR | H22: Total MRR
A23: Q1 | B23: 75000 | C23: 69000 | D23: 5250 | E23: 750 | F23: =D23*Assumptions!$B$26 | G23: =E23*Assumptions!$B$27 | H23: =F23+G23
A24: Q2 | B24: 112500 | C24: 103500 | D24: 7875 | E24: 1125 | F24: =D24*Assumptions!$B$26 | G24: =E24*Assumptions!$B$27 | H24: =F24+G24
A25: Q3 | B25: 150000 | C25: 138000 | D25: 10500 | E25: 1500 | F25: =D25*Assumptions!$B$26 | G25: =E25*Assumptions!$B$27 | H25: =F25+G25
A26: Q4 | B26: 200000 | C26: 184000 | D26: 14000 | E26: 2000 | F26: =D26*Assumptions!$B$26 | G26: =E26*Assumptions!$B$27 | H26: =F26+G26
A28: YEAR 3 - QUARTERLY PROJECTIONS
A29: Quarter | B29: Total Users | C29: Free Users | D29: Premium | E29: Pro | F29: Premium MRR | G29: Pro MRR | H29: Total MRR
A30: Q1 | B30: 260000 | C30: 237900 | D30: 19500 | E30: 2600 | F30: =D30*Assumptions!$B$26 | G30: =E30*Assumptions!$B$27 | H30: =F30+G30
A31: Q2 | B31: 340000 | C31: 311100 | D31: 25500 | E31: 3400 | F31: =D31*Assumptions!$B$26 | G31: =E31*Assumptions!$B$27 | H31: =F31+G31
A32: Q3 | B32: 450000 | C32: 411750 | D32: 33750 | E32: 4500 | F32: =D32*Assumptions!$B$26 | G32: =E32*Assumptions!$B$27 | H32: =F32+G32
A33: Q4 | B33: 600000 | C33: 549000 | D33: 45000 | E33: 6000 | F33: =D33*Assumptions!$B$26 | G33: =E33*Assumptions!$B$27 | H33: =F33+G33
A35: ANNUAL REVENUE SUMMARY
A36: Year | B36: Conservative | C36: Moderate | D36: Aggressive
A37: Year 1 | B37: 120000 | C37: 180000 | D37: 300000
A38: Year 2 | B38: 800000 | C38: 1800000 | D38: 3500000
A39: Year 3 | B39: 2500000 | C39: 6480000 | D39: 12000000

Sheet Cost Structure
A1: COST STRUCTURE
A3: FIXED COSTS (MONTHLY)
A4: Category | B4: Year 1 | C4: Year 2 | D4: Year 3
A5: PERSONNEL
A6: Engineering (FTEs) (1.5) | B6: 12500 | C6: 33333 | D6: 75000
A7: Marketing (FTEs) (0.5) | B7: 4167 | C7: 8333 | D7: 16667
A8: Operations (FTEs) (0) | B8: 0 | C8: 4167 | D8: 8333
A9: Subtotal Personnel | B9: =SUM(B6:B8) | C9: =SUM(C6:C8) | D9: =SUM(D6:D8)
A11: INFRASTRUCTURE
A12: Hosting (Netlify/AWS) | B12: 200 | C12: 800 | D12: 2500
A13: CDN & Storage | B13: 100 | C13: 400 | D13: 1000
A14: Dev Tools & Services | B14: 200 | C14: 400 | D14: 800
A15: Subtotal Infrastructure | B15: =SUM(B12:B14) | C15: =SUM(C12:C14) | D15: =SUM(D12:D14)
A17: OPERATIONS
A18: Legal & Compliance | B18: 500 | C18: 1000 | D18: 2000
A19: Accounting | B19: 300 | C19: 600 | D19: 1200
A20: Insurance | B20: 200 | C20: 400 | D20: 800
A21: Office/Misc | B21: 200 | C21: 400 | D21: 1000
A22: Subtotal Operations | B22: =SUM(B18:B21) | C22: =SUM(C18:C21) | D22: =SUM(D18:D21)
A24: TOTAL FIXED COSTS | B24: =B9+B15+B22 | C24: =C9+C15+C22 | D24: =D9+D15+D22
A27: VARIABLE COSTS
A28: API Costs | B28: 2500 | C28: 8000 | D28: 18000
A29: Payment Processing (2.9%) | B29: 500 | C29: 5500 | D29: 19000
A30: Customer Support | B30: 1000 | C30: 4000 | D30: 12000
A31: Marketing Spend | B31: 8333 | C31: 25000 | D31: 50000
A32: TOTAL VARIABLE COSTS | B32: =SUM(B28:B31) | C32: =SUM(C28:C31) | D32: =SUM(D28:D31)
A35: TOTAL MONTHLY COSTS | B35: =B24+B32 | C35: =C24+C32 | D35: =D24+D32
A37: ANNUAL COSTS | B37: =B35*12 | C37: =C35*12 | D37: =D35*12

Sheet P&L Projection
A1: P&L PROJECTION - MODERATE SCENARIO
A3: YEAR 1
A4: Line Item | B4: Q1 | C4: Q2 | D4: Q3 | E4: Q4 | F4: Year 1 Total
A5: REVENUE
A6: Premium Revenue | B6: 5000 | C6: 15000 | D6: 35000 | E6: 65000
A7: Pro Revenue | B7: 2000 | C7: 6000 | D7: 14000 | E7: 38000
A8: Total Revenue | B8: =B6+B7 | C8: =C6+C7 | D8: =D6+D7 | E8: =E6+E7 | F8: =SUM(B8:E8)
A10: COGS
A11: API Costs | B11: 1500 | C11: 3000 | D11: 5000 | E11: 8000
A12: Payment Processing | B12: 300 | C12: 800 | D12: 1800 | E12: 3500
A13: Support | B13: 500 | C13: 1500 | D13: 3000 | E13: 5000
A14: Total COGS | B14: =SUM(B11:B13) | C14: =SUM(C11:C13) | D14: =SUM(D11:D13) | E14: =SUM(E11:E13) | F14: =SUM(B14:E14)
A16: Gross Profit | B16: =B8-B14 | C16: =C8-C14 | D16: =D8-D14 | E16: =E8-E14 | F16: =F8-F14
A17: Gross Margin % | B17: =B16/B8 | C17: =C16/C8 | D17: =D16/D8 | E17: =E16/E8 | F17: =F16/F8
A19: OPERATING EXPENSES
A20: Personnel | B20: 50000 | C20: 50000 | D20: 50000 | E20: 50000
A21: Infrastructure | B21: 1500 | C21: 1500 | D21: 1500 | E21: 1500
A22: Marketing | B22: 25000 | C22: 25000 | D22: 25000 | E22: 25000
A23: Operations | B23: 3600 | C23: 3600 | D23: 3600 | E23: 3600
A24: Total OpEx | B24: =SUM(B20:B23) | C24: =SUM(C20:C23) | D24: =SUM(D20:D23) | E24: =SUM(E20:E23) | F24: =SUM(B24:E24)
A26: EBITDA | B26: =B16-B24 | C26: =C16-C24 | D26: =D16-D24 | E26: =E16-E24 | F26: =F16-F24
A27: EBITDA Margin % | B27: =B26/B8 | C27: =C26/C8 | D27: =D26/D8 | E27: =E26/E8 | F27: =F26/F8
A30: YEAR 2
A31: Line Item | B31: Q1 | C31: Q2 | D31: Q3 | E31: Q4 | F31: Year 1 Total
A32: REVENUE
A33: Premium Revenue | B33: 150000 | C33: 250000 | D33: 380000 | E33: 540000
A34: Pro Revenue | B34: 45000 | C34: 75000 | D34: 115000 | E34: 165000
A35: Total Revenue | B35: =B33+B34 | C35: =C33+C34 | D35: =D33+D34 | E35: =E33+E34 | F35: =SUM(B35:E35)
A37: COGS (15%) | B37: =B35*0.15 | C37: =C35*0.15 | D37: =D35*0.15 | E37: =E35*0.15 | F37: =SUM(B37:E37)
A38: Gross Profit | B38: =B35-B37 | C38: =C35-C37 | D38: =D35-D37 | E38: =E35-E37 | F38: =F35-F37
A39: Gross Margin % | B39: =B38/B35 | C39: =C38/C35 | D39: =D38/D35 | E39: =E38/E35 | F39: =F38/F35
A41: Operating Expenses | B41: 200000 | C41: 225000 | D41: 250000 | E41: 275000 | F41: =SUM(B41:E41)
A43: EBITDA | B43: =B38-B41 | C43: =C38-C41 | D43: =D38-D41 | E43: =E38-E41 | F43: =F38-F41
A44: EBITDA Margin % | B44: =B43/B35 | C44: =C43/C35 | D44: =D43/D35 | E44: =E43/E35 | F44: =F43/F35

Sheet Break-even Analysis
A1: BREAK-EVEN ANALYSIS
A3: SCENARIO COMPARISON
A4: Scenario | B4: Monthly Fixed Costs | C4: Avg Revenue/User | D4: Users to Break-even | E4: Timeline
A5: Conservative | B5: 25000 | C5: 11 | D5: 2273 | E5: Month 22
A6: Moderate | B6: 30000 | C6: 12 | D6: 2500 | E6: Month 16
A7: Aggressive | B7: 35000 | C7: 13 | D7: 2692 | E7: Month 12
A10: MONTHLY BREAK-EVEN TRAJECTORY
A11: Month | B11: Revenue | C11: Costs | D11: Cumulative P/L | E11: Status
A12: 6 | B12: 8000 | C12: 28000 | D12: -120000 | E12: Below
A13: 12 | B13: 25000 | C13: 32000 | D13: -200000 | E13: Below
A14: 16 | B14: 50000 | C14: 45000 | D14: -180000 | E14: Break-even
A15: 18 | B15: 70000 | C15: 55000 | D15: -150000 | E15: Above
A16: 24 | B16: 150000 | C16: 90000 | D16: 100000 | E16: Profitable
A19: CASH FLOW TO BREAK-EVEN
A20: Period | B20: Revenue | C20: Expenses | D20: Net Cash | E20: Cumulative
A21: Months 1-6 | B21: 45000 | C21: 175000 | D21: -130000 | E21: -130000
A22: Months 7-12 | B22: 135000 | C22: 195000 | D22: -60000 | E22: -190000
A23: Months 13-16 | B23: 180000 | C23: 180000 | D23: 0 | E23: -190000
A24: Months 17-24 | B24: 600000 | C24: 480000 | D24: 120000 | E24: -70000
A25: Months 25-36 | B25: 4500000 | C25: 2150000 | D25: 2350000 | E25: 2280000

Sheet Sensitivity Analysis
A1: SENSITIVITY ANALYSIS
A3: CONVERSION RATE IMPACT (Y3 Revenue)
A4: Premium Conversion | B4: 4% | C4: 5% | D4: 6% | E4: 7% | F4: 8%
A5: Revenue | B5: 4200000 | C5: 5200000 | D5: 6100000 | E5: 7100000 | F5: 8000000
A6: Change from Baseline | B6: -31% | C6: -15% | D6: Baseline | E6: +16% | F6: +31%
A9: PRICING IMPACT (Y3 Revenue @ 6% conversion)
A10: Premium Price | B10: $7.99 | C10: $8.99 | D10: $9.99 | E10: $11.99 | F10: $14.99
A11: Revenue | B11: 4900000 | C11: 5500000 | D11: 6100000 | E11: 7300000 | F11: 9100000
A12: Change from Baseline | B12: -20% | C12: -10% | D12: Baseline | E12: +20% | F12: +49%
A15: CHURN IMPACT (Y3 Revenue)
A16: Monthly Churn | B16: 3% | C16: 4% | D16: 5% | E16: 6% | F16: 7%
A17: Revenue | B17: 7000000 | C17: 6500000 | D17: 6100000 | E17: 5700000 | F17: 5300000
A18: Change from Baseline | B18: +15% | C18: +7% | D18: Baseline | E18: -7% | F18: -13%
A21: CAC IMPACT ON Y3 EBITDA
A22: CAC | B22: $10 | C22: $15 | D22: $20 | E22: $25 | F22: $30
A23: Y3 EBITDA | B23: 3500000 | C23: 3000000 | D23: 2500000 | E23: 2000000 | F23: 1500000
A24: Break-even Month | B24: Mo 12 | C24: Mo 16 | D24: Mo 20 | E24: Mo 24 | F24: Mo 28
A27: SCENARIO SUMMARY
A28: Scenario | B28: Y1 Revenue | C28: Y3 Revenue | D28: Y3 EBITDA | E28: Break-even
A29: Conservative | B29: 120000 | C29: 2500000 | D29: 500000 | E29: Month 22
A30: Moderate | B30: 180000 | C30: 6100000 | D30: 3000000 | E30: Month 16
A31: Aggressive | B31: 300000 | C31: 12000000 | D31: 7000000 | E31: Month 12

Sheet Unit Economics
A1: UNIT ECONOMICS
A3: CUSTOMER LIFETIME VALUE (LTV)
A4: Tier | B4: Monthly Price | C4: Avg Tenure | D4: Gross LTV | E4: Net LTV (after churn)
A5: Premium | B5: 9.99 | C5: 14 months | D5: 140 | E5: 120
A6: Pro | B6: 19.99 | C6: 18 months | D6: 360 | E6: 320
A7: Blended | B7: 12.5 | C7: 15 months | D7: 188 | E7: 160
A10: CUSTOMER ACQUISITION COST (CAC)
A11: Channel | B11: CAC | C11: % of Budget | D11: Weighted CAC
A12: Organic/SEO | B12: 5 | C12: 30% | D12: 1.5
A13: Content Marketing | B13: 10 | C13: 20% | D13: 2
A14: Paid Social | B14: 20 | C14: 25% | D14: 5
A15: Paid Search | B15: 25 | C15: 15% | D15: 3.75
A16: Influencers | B16: 18 | C16: 10% | D16: 1.8
A17: Blended CAC | C17: 100% | D17: 14.05
A19: LTV:CAC ANALYSIS
A20: Metric | B20: Premium | C20: Pro | D20: Blended
A21: LTV | B21: 120 | C21: 320 | D21: 160
A22: CAC | B22: 14 | C22: 14 | D22: 14
A23: LTV:CAC | B23: =B21/B22 | C23: =C21/C22 | D23: =D21/D22
A24: Payback (months) | B24: 1.4 | C24: 0.7 | D24: 1.1
A27: UNIT ECONOMICS BY YEAR
A28: Metric | B28: Year 1 | C28: Year 2 | D28: Year 3
A29: CAC | B29: 18 | C29: 14 | D29: 12
A30: LTV | B30: 100 | C30: 150 | D30: 180
A31: LTV:CAC | B31: =B30/B29 | C31: =C30/C29 | D31: =D30/D29
A32: Payback (months) | B32: 1.8 | C32: 1.2 | D32: 0.8

Sheet Funding & Runway
A1: FUNDING & RUNWAY ANALYSIS
A3: FUNDING ASK
A4: Seed Round | B4: 500000 | C4: 18-month runway to break-even
A7: USE OF FUNDS
A8: Category | B8: Amount | C8: % of Total | D8: Purpose
A9: Engineering | B9: 200000 | C9: 0.4 | D9: 2 additional engineers (12 mo)
A10: Marketing | B10: 150000 | C10: 0.3 | D10: User acquisition, content, brand
A11: Infrastructure | B11: 50000 | C11: 0.1 | D11: Hosting, APIs, tools
A12: Operations | B12: 50000 | C12: 0.1 | D12: Legal, accounting, office
A13: Buffer | B13: 50000 | C13: 0.1 | D13: Contingency
A15: Total | B15: =SUM(B9:B13)
A18: RUNWAY ANALYSIS
A19: Scenario | B19: Monthly Burn | C19: Runway (with $500K) | D19: Break-even
A20: Conservative | B20: 35000 | C20: 14 months | D20: Month 22 (needs bridge)
A21: Moderate | B21: 30000 | C21: 17 months | D21: Month 16 ✅
A22: Aggressive | B22: 25000 | C22: 20 months | D22: Month 12 ✅
A25: FUNDING MILESTONES
A26: Milestone | B26: Target | C26: Timeline
A27: Seed Close | B27: $500K | C27: Month 0
A28: 10,000 Users | B28: Acquisition | C28: Month 6
A29: 1,000 Paying Users | B29: Monetization | C29: Month 9
A30: $25K MRR | B30: Traction | C30: Month 12
A31: Break-even | B31: Sustainability | C31: Month 16
A32: Series A Readiness | B32: Growth metrics | C32: Month 18
A35: VALUATION SCENARIOS
A36: Scenario | B36: Y3 Revenue | C36: Multiple | D36: Valuation
A37: Conservative | B37: 2500000 | C37: 8x | D37: =B37*8
A38: Moderate | B38: 6100000 | C38: 10x | D38: =B38*10
A39: Aggressive | B39: 12000000 | C39: 12x | D39: =B39*12
A42: INVESTOR RETURNS (20% equity for $500K)
A43: Scenario | B43: Valuation | C43: Investor Stake (20%) | D43: Return Multiple
A44: Conservative | B44: =D37 | C44: =B44*0.20 | D44: =C44/500000
A45: Moderate | B45: =D38 | C45: =B45*0.20 | D45: =C45/500000
A46: Aggressive | B46: =D39 | C46: =B46*0.20 | D46: =C46/500000
